{"stats":{"minecraft:custom":{"minecraft:time_since_rest":9158,"minecraft:open_chest":1,"jcraft:dashes":5,"minecraft:crouch_one_cm":514,"minecraft:deaths":1,"minecraft:sprint_one_cm":49093,"minecraft:play_time":9500,"minecraft:walk_one_cm":27025,"minecraft:damage_taken":498,"minecraft:damage_absorbed":12,"minecraft:sneak_time":106,"minecraft:jump":106,"minecraft:leave_game":2,"minecraft:time_since_death":9096,"minecraft:climb_one_cm":28,"minecraft:total_world_time":9500,"minecraft:interact_with_crafting_table":1,"minecraft:fly_one_cm":27796,"minecraft:fall_one_cm":2062},"minecraft:picked_up":{"minecraft:crafting_table":1,"minecraft:iron_leggings":1,"minecraft:bone":2,"pointblank:ammo9mm":47,"minecraft:hay_block":8},"minecraft:used":{"minecraft:crafting_table":1,"minecraft:bread":4,"minecraft:iron_leggings":1},"minecraft:killed_by":{"minecraft:player":1},"minecraft:crafted":{"minecraft:bread":24,"minecraft:wheat":72}},"DataVersion":3465}